{
  "type": "FeatureCollection",
  "name": "train_stations",
  "crs": {
    "type": "name",
    "properties": { "name": "urn:ogc:def:crs:OGC:1.3:CRS84" }
  },
  "features": [
    {
      "type": "Feature",
      "properties": {
        "id": 1,
        "name": "Trechtingshausen",
        "desc": "This is the stop for Burg Reichenstein where we stayed at."
      },
      "geometry": { "type": "Point", "coordinates": [7.85195, 50.00959] }
    },
    {
      "type": "Feature",
      "properties": {
        "id": 2,
        "name": "Bingen Hauptbahnhof",
        "desc": "This is the first stop for Bingen."
      },
      "geometry": { "type": "Point", "coordinates": [7.88348, 49.96868] }
    },
    {
      "type": "Feature",
      "properties": {
        "id": 3,
        "name": "Bingen Stadt",
        "desc": "This is the second stop for Bingen and where we got off to get to the dock."
      },
      "geometry": { "type": "Point", "coordinates": [7.90372, 49.96974] }
    }
  ]
}
